torchabc/__init__.py
torchabc/cli.py
torchabc-0.6.3.dist-info/LICENSE
torchabc-0.6.3.dist-info/METADATA
torchabc-0.6.3.dist-info/WHEEL
torchabc-0.6.3.dist-info/entry_points.txt
torchabc-0.6.3.dist-info/RECORD
