Metadata-Version: 2.3
Name: torchabc
Version: 0.6.3
Summary: A simple abstract class for training and inference in PyTorch.
License: MIT
Author: Emanuele Guidotti
Author-email: emanuele.guidotti@usi.ch
Requires-Python: >=3.9
Classifier: License :: OSI Approved :: MIT License
Classifier: Programming Language :: Python :: 3
Classifier: Programming Language :: Python :: 3.9
Classifier: Programming Language :: Python :: 3.10
Classifier: Programming Language :: Python :: 3.11
Classifier: Programming Language :: Python :: 3.12
Classifier: Programming Language :: Python :: 3.13
Requires-Dist: torch (>=2.6.0,<3.0.0)
Project-URL: Homepage, https://github.com/eguidotti/torchabc
Project-URL: Repository, https://github.com/eguidotti/torchabc
